print2d/__init__.py
print2d/_print2d_list.py
print2d/_print2d_np.py
print2d/_print2d_torch.py
print2d-0.2.1.dist-info/LICENSE
print2d-0.2.1.dist-info/METADATA
print2d-0.2.1.dist-info/WHEEL
print2d-0.2.1.dist-info/top_level.txt
print2d-0.2.1.dist-info/RECORD
