Metadata-Version: 2.1
Name: print2d
Version: 0.2.1
Summary: print2d : Replacement of `print()` for printing 2d array with readability.
Home-page: https://github.com/pjessesco/print2d
Author: Jino Park
Author-email: pjessesco@gmail.com
License: MIT
Platform: UNKNOWN
Classifier: Programming Language :: Python :: 3
Classifier: License :: OSI Approved :: MIT License
Classifier: Operating System :: OS Independent
